setup.py
miscpy/Loading.py
miscpy/Saving.py
miscpy/String.py
miscpy/__init__.py
miscpy.egg-info/PKG-INFO
miscpy.egg-info/SOURCES.txt
miscpy.egg-info/dependency_links.txt
miscpy.egg-info/top_level.txt