Metadata-Version: 1.0
Name: miscpy
Version: 0.2.20
Summary: miscpy facilitates (scientific) python scripting. It helps file and  data handling through various miscellaneous functions and extending the string class.
Home-page: https://github.com/manuSrep/miscpy.git
Author: Manuel Tuschen
Author-email: Manuel_Tuschen@web.de
License: FreeBSD License
Platform: UNKNOWN
